seven_wallpaper/__init__.py
seven_wallpaper/app_encrypt.py
seven_wallpaper/bd_censor.py
seven_wallpaper/bd_login.py
seven_wallpaper/file_upload.py
seven_wallpaper/useranget.py
seven_wallpaper/wallpaper_elasticsearch.py
seven_wallpaper/wallpaper_memcache.py
seven_wallpaper/wallpaper_redis.py
seven_wallpaper/bizhi_web/__init__.py
seven_wallpaper/bizhi_web/bizhi_base_handler.py
seven_wallpaper-1.0.0.dist-info/METADATA
seven_wallpaper-1.0.0.dist-info/WHEEL
seven_wallpaper-1.0.0.dist-info/top_level.txt
seven_wallpaper-1.0.0.dist-info/RECORD
