Metadata-Version: 2.1
Name: seven-wallpaper
Version: 1.0.0
Summary: wallpaper project base framework
Home-page: UNKNOWN
Author: huangwenbin
Author-email: UNKNOWN
License: UNKNOWN
Platform: UNKNOWN
Requires-Dist: seven-framework >=1.1.32
